moralstrength/__init__.py
moralstrength/data.py
moralstrength/estimators.py
moralstrength/lexicon_use.py
moralstrength/moral_list.py
moralstrength/moralstrength.py
moralstrength/moralstrengthdict.py
moralstrength/annotations/authority.tsv
moralstrength/annotations/care.tsv
moralstrength/annotations/fairness.tsv
moralstrength/annotations/loyalty.tsv
moralstrength/annotations/purity.tsv
moralstrength/annotations/v1.1/authority.tsv
moralstrength/annotations/v1.1/care.tsv
moralstrength/annotations/v1.1/fairness.tsv
moralstrength/annotations/v1.1/lexicons_expanded_v1-1.pck
moralstrength/annotations/v1.1/loyalty.tsv
moralstrength/annotations/v1.1/purity.tsv
moralstrength/export/count_authority_lr.pck
moralstrength/export/count_care_lr.pck
moralstrength/export/count_fairness_lr.pck
moralstrength/export/count_loyalty_lr.pck
moralstrength/export/count_non-moral_lr.pck
moralstrength/export/count_purity_lr.pck
moralstrength/export/freq_authority_lr.pck
moralstrength/export/freq_care_lr.pck
moralstrength/export/freq_fairness_lr.pck
moralstrength/export/freq_loyalty_lr.pck
moralstrength/export/freq_non-moral_lr.pck
moralstrength/export/freq_purity_lr.pck
moralstrength/export/ngram.pck
moralstrength/export/unigram+count+freq_authority_lr.pck
moralstrength/export/unigram+count+freq_care_lr.pck
moralstrength/export/unigram+count+freq_fairness_lr.pck
moralstrength/export/unigram+count+freq_loyalty_lr.pck
moralstrength/export/unigram+count+freq_non-moral_lr.pck
moralstrength/export/unigram+count+freq_purity_lr.pck
moralstrength/export/unigram+count_authority_lr.pck
moralstrength/export/unigram+count_care_lr.pck
moralstrength/export/unigram+count_fairness_lr.pck
moralstrength/export/unigram+count_loyalty_lr.pck
moralstrength/export/unigram+count_non-moral_lr.pck
moralstrength/export/unigram+count_purity_lr.pck
moralstrength/export/unigram+freq_authority_lr.pck
moralstrength/export/unigram+freq_care_lr.pck
moralstrength/export/unigram+freq_fairness_lr.pck
moralstrength-0.2.13.dist-info/LICENSE.txt
moralstrength-0.2.13.dist-info/METADATA
moralstrength-0.2.13.dist-info/WHEEL
moralstrength-0.2.13.dist-info/top_level.txt
moralstrength-0.2.13.dist-info/RECORD
