Metadata-Version: 2.1
Name: moralstrength
Version: 0.2.13
Summary: A package to predict the Moral Foundations for a tweet or text
Home-page: https://github.com/oaraque/moral-foundations/
Download-URL: https://github.com/oaraque/moral-foundations/tarball/0.2.13
Author: Oscar Araque, Lorenzo Gatti and Kyriaki Kalimeri
Author-email: o.araque@upm.es
License: LGPLv3
Keywords: moral foundations,NLP,moralstrength,machine learning
Classifier: Intended Audience :: Science/Research
Classifier: Natural Language :: English
Classifier: Topic :: Text Processing :: Linguistic
Classifier: Programming Language :: Python :: 3
Classifier: License :: OSI Approved :: GNU Lesser General Public License v3 (LGPLv3)
Classifier: Operating System :: OS Independent
License-File: LICENSE.txt
Requires-Dist: spacy
Requires-Dist: pandas
Requires-Dist: gsitk
Requires-Dist: numpy
Requires-Dist: scikit-learn
